arp_auth/__init__.py
arp_auth/client.py
arp_auth/errors.py
arp_auth/py.typed
arp_auth-0.2.1.dist-info/licenses/LICENSE
arp_auth-0.2.1.dist-info/METADATA
arp_auth-0.2.1.dist-info/WHEEL
arp_auth-0.2.1.dist-info/top_level.txt
arp_auth-0.2.1.dist-info/RECORD
