Metadata-Version: 2.4
Name: arp-auth
Version: 0.2.1
Summary: Auth helpers for ARP components (OIDC client credentials and token exchange).
Author: Agent Runtime Protocol
License-Expression: MIT
Project-URL: Repository, https://github.com/AgentRuntimeProtocol/ARP_Auth
Project-URL: Issues, https://github.com/AgentRuntimeProtocol/ARP_Auth/issues
Classifier: Programming Language :: Python :: 3
Classifier: Programming Language :: Python :: 3 :: Only
Classifier: Programming Language :: Python :: 3.11
Classifier: Programming Language :: Python :: 3.12
Classifier: Programming Language :: Python :: 3.13
Classifier: Programming Language :: Python :: 3.14
Classifier: Typing :: Typed
Requires-Python: >=3.11
License-File: LICENSE
Provides-Extra: dev
Requires-Dist: pytest>=7; extra == "dev"
Requires-Dist: pyright>=1.1.0; extra == "dev"
Dynamic: license-file
